VoiceInsights-0.0.2.dist-info/DESCRIPTION.rst
VoiceInsights-0.0.2.dist-info/METADATA
VoiceInsights-0.0.2.dist-info/RECORD
VoiceInsights-0.0.2.dist-info/WHEEL
VoiceInsights-0.0.2.dist-info/metadata.json
VoiceInsights-0.0.2.dist-info/top_level.txt
voicelabs/__init__.py
voicelabs/voicelabs.py
