Metadata-Version: 2.0
Name: VoiceInsights
Version: 0.0.2
Summary: VoiceInsights Python SDK
Home-page: https://github.com/voicelabs/analytics-python-sdk
Author: Sridhar Nallani
Author-email: sridhar@voicelabs.co
License: MIT
Keywords: voicelabs,voiceinsights,alexasdk
Platform: UNKNOWN
Classifier: Intended Audience :: Developers
Classifier: Topic :: Software Development :: Build Tools
Classifier: License :: OSI Approved :: MIT License
Classifier: Programming Language :: Python :: 2.7
Requires-Dist: requests
